tubex_lib/__init__.py
tubex_lib/tube.cp38-win_amd64.pyd
tubex_lib/version.py
tubex_lib/tests/__init__.py
tubex_lib/tests/test_arithmetic.py
tubex_lib/tests/test_cn.py
tubex_lib/tests/test_ctc_constell.py
tubex_lib/tests/test_ctcdelay.py
tubex_lib/tests/test_ctceval.py
tubex_lib/tests/test_definition.py
tubex_lib/tests/test_function.py
tubex_lib/tests/test_multi_arithmetic.py
tubex_lib-3.1.1.dist-info/METADATA
tubex_lib-3.1.1.dist-info/WHEEL
tubex_lib-3.1.1.dist-info/top_level.txt
tubex_lib-3.1.1.dist-info/RECORD
