Metadata-Version: 2.1
Name: tubex-lib
Version: 3.1.1
Summary: Tubex is a library providing tools for constraint programming over reals and trajectories.
Home-page: http://simon-rohou.fr/research/tubex-lib
Author: Simon Rohou, Benoit Desrochers
Author-email: simon.rohou@ensta-bretagne.fr
License: LGPLv3+
Platform: UNKNOWN
Classifier: Development Status :: 3 - Alpha
Classifier: Topic :: Scientific/Engineering :: Mathematics
Classifier: License :: OSI Approved :: GNU Lesser General Public License v3 or later (LGPLv3+)
Requires-Dist: pip (>=19.0.0)
Requires-Dist: pyibex (>=1.9.2)
